data_to_paper/__init__.py
data_to_paper/env.py
data_to_paper/exceptions.py
data_to_paper/types.py
data_to_paper/base_cast/__init__.py
data_to_paper/base_cast/cast.py
data_to_paper/base_cast/types.py
data_to_paper/base_products/__init__.py
data_to_paper/base_products/file_descriptions.py
data_to_paper/base_products/product.py
data_to_paper/base_products/products.py
data_to_paper/base_steps/__init__.py
data_to_paper/base_steps/base_products_conversers.py
data_to_paper/base_steps/base_products_to_file.py
data_to_paper/base_steps/base_steps_runner.py
data_to_paper/base_steps/converser.py
data_to_paper/base_steps/copier.py
data_to_paper/base_steps/debugger.py
data_to_paper/base_steps/dual_converser.py
data_to_paper/base_steps/exceptions.py
data_to_paper/base_steps/latex_products_to_pdf.py
data_to_paper/base_steps/literature_search.py
data_to_paper/base_steps/request_code.py
data_to_paper/base_steps/request_latex.py
data_to_paper/base_steps/request_literature_search.py
data_to_paper/base_steps/request_multi_choice.py
data_to_paper/base_steps/request_products_from_user.py
data_to_paper/base_steps/request_python_value.py
data_to_paper/base_steps/request_quoted_text.py
data_to_paper/base_steps/result_converser.py
data_to_paper/base_steps/run_all_steps.py
data_to_paper/code_and_output_files/__init__.py
data_to_paper/code_and_output_files/code_and_output.py
data_to_paper/code_and_output_files/file_view_params.py
data_to_paper/code_and_output_files/output_file_requirements.py
data_to_paper/code_and_output_files/ref_numeric_values.py
data_to_paper/code_and_output_files/referencable_text.py
data_to_paper/conversation/__init__.py
data_to_paper/conversation/actions_and_conversations.py
data_to_paper/conversation/conversation.py
data_to_paper/conversation/conversation_actions.py
data_to_paper/conversation/conversation_manager.py
data_to_paper/conversation/message.py
data_to_paper/conversation/message_designation.py
data_to_paper/conversation/replay.py
data_to_paper-1.1.21.dist-info/licenses/LICENSE
data_to_paper-1.1.21.dist-info/METADATA
data_to_paper-1.1.21.dist-info/WHEEL
data_to_paper-1.1.21.dist-info/entry_points.txt
data_to_paper-1.1.21.dist-info/top_level.txt
data_to_paper-1.1.21.dist-info/RECORD
