Metadata-Version: 2.4
Name: data_to_paper
Version: 1.1.21
Summary: data-to-paper: Backward-traceable AI-driven scientific research
Author: Kishony lab, Technion Israel Institute of Technology
Author-email: Roy Kishony <rkishony@technion.ac.il>, Tal Ifargan <talifargan@campus.technion.ac.il>, Lukas Hafner <lukashafner@campus.technion.ac.il>
License: MIT License
Project-URL: Repository, https://github.com/Technion-Kishony-lab/data-to-paper
Keywords: data-to-paper,research,AI-driven-research,backward-traceable,ai,agents,autonomous-agents,scientific-research,interactive-machine-learning,llm
Classifier: Intended Audience :: Education
Classifier: Intended Audience :: Science/Research
Classifier: Intended Audience :: Healthcare Industry
Classifier: Intended Audience :: Information Technology
Classifier: Topic :: Scientific/Engineering
Classifier: Topic :: Scientific/Engineering :: Visualization
Classifier: License :: OSI Approved :: MIT License
Classifier: Programming Language :: Python
Classifier: Operating System :: OS Independent
Requires-Python: >=3.9
License-File: LICENSE
Requires-Dist: colorama==0.4.6
Requires-Dist: openai==0.27.8
Requires-Dist: regex==2023.6.3
Requires-Dist: tiktoken==0.4.0
Requires-Dist: pygments~=2.15.1
Requires-Dist: requests~=2.31.0
Requires-Dist: unidecode~=1.3.6
Requires-Dist: PyMuPDF~=1.23.20
Requires-Dist: py-spy~=0.3.14
Requires-Dist: ansi2html~=1.8.0
Requires-Dist: PySide6==6.5.2
Requires-Dist: pytest~=7.4.0
Requires-Dist: numpy~=1.25.1
Requires-Dist: pandas==2.0.3
Requires-Dist: Jinja2~=3.1.4
Requires-Dist: statsmodels~=0.14.0
Requires-Dist: scipy~=1.11.1
Requires-Dist: scikit-learn~=1.3.0
Requires-Dist: networkx~=3.2.1
Requires-Dist: matplotlib~=3.9.0
Provides-Extra: dev
Requires-Dist: pytest; extra == "dev"
Requires-Dist: pytest-pep8; extra == "dev"
Requires-Dist: pytest-cov; extra == "dev"
Requires-Dist: pytest-benchmark; extra == "dev"
Dynamic: license-file
